gallagher_restapi/__init__.py
gallagher_restapi/client.py
gallagher_restapi/exceptions.py
gallagher_restapi/models.py
gallagher_restapi/py.typed
gallagher_restapi-2.1.0.dist-info/WHEEL
gallagher_restapi-2.1.0.dist-info/METADATA
gallagher_restapi-2.1.0.dist-info/RECORD
