Metadata-Version: 2.4
Name: gallagher-restapi
Version: 2.1.0
Summary: Python library for Gallagher REST API
Author: Rami Mousleh
Author-email: Rami Mousleh <rami.mousleh@gallagher-me.com>
License-Expression: MIT
Requires-Dist: httpx>=0.28.1,<1.0.0
Requires-Dist: pytz>=2025.2
Requires-Dist: pydantic>=2.12.3,<3.0.0
Requires-Python: >=3.11
